robotframework_historic2/__init__.py
robotframework_historic2/app.py
robotframework_historic2/args.py
robotframework_historic2/parserargs.py
robotframework_historic2/reparserargs.py
robotframework_historic2/rfhistoricparser.py
robotframework_historic2/rfhistoricreparser.py
robotframework_historic2/rfhistoricsetup.py
robotframework_historic2/setupargs.py
robotframework_historic2/templates/comment.html
robotframework_historic2/templates/compare.html
robotframework_historic2/templates/dashboardAll.html
robotframework_historic2/templates/dashboardByEid.html
robotframework_historic2/templates/dashboardRecent.html
robotframework_historic2/templates/dashboardRecentFive.html
robotframework_historic2/templates/dashboardRecentTen.html
robotframework_historic2/templates/dashboardRecentThirty.html
robotframework_historic2/templates/deldbconf.html
robotframework_historic2/templates/deleconf.html
robotframework_historic2/templates/ehistoric.html
robotframework_historic2/templates/eidtmetrics.html
robotframework_historic2/templates/failures.html
robotframework_historic2/templates/flaky.html
robotframework_historic2/templates/home.html
robotframework_historic2/templates/newdb.html
robotframework_historic2/templates/query.html
robotframework_historic2/templates/redirect.html
robotframework_historic2/templates/search.html
robotframework_historic2/templates/tmetrics.html
robotframework_historic2/templates/ttags.html
robotframework_historic2/templates/updatedb.html
robotframework_historic2/templates/assets/css/dashboard.css
robotframework_historic2/templates/assets/fonts/feather/feather-webfont.eot
robotframework_historic2/templates/assets/fonts/feather/feather-webfont.svg
robotframework_historic2/templates/assets/fonts/feather/feather-webfont.ttf
robotframework_historic2/templates/assets/fonts/feather/feather-webfont.woff
robotframework_historic2/templates/assets/js/core.js
robotframework_historic2/templates/assets/js/dashboard.js
robotframework_historic2-0.0.1.dist-info/LICENSE
robotframework_historic2-0.0.1.dist-info/METADATA
robotframework_historic2-0.0.1.dist-info/WHEEL
robotframework_historic2-0.0.1.dist-info/entry_points.txt
robotframework_historic2-0.0.1.dist-info/top_level.txt
robotframework_historic2-0.0.1.dist-info/RECORD
