Metadata-Version: 2.1
Name: robotframework-historic2
Version: 0.0.1
Summary: Custom report to display robotframework historical execution records
Home-page: https://github.com/adiralashiva8/robotframework-historic
Author: Shiva Prasad Adirala
Author-email: adiralashiva8@gmail.com
License: MIT
Keywords: robotframework historical execution report
Platform: UNKNOWN
Classifier: Framework :: Robot Framework
Classifier: Programming Language :: Python
Classifier: Topic :: Software Development :: Testing
License-File: LICENSE
Requires-Dist: robotframework
Requires-Dist: config
Requires-Dist: flask
Requires-Dist: flask-mysqldb
